tasks/__init__.py
tasks/super_functions.py
tasks/tasks.py
tasks_genrator-0.1.dist-info/LICENSE
tasks_genrator-0.1.dist-info/METADATA
tasks_genrator-0.1.dist-info/WHEEL
tasks_genrator-0.1.dist-info/top_level.txt
tasks_genrator-0.1.dist-info/RECORD
